jack_social_checker/__init__.py
jack_social_checker/checker.py
jack_social_checker-0.1.0.dist-info/METADATA
jack_social_checker-0.1.0.dist-info/WHEEL
jack_social_checker-0.1.0.dist-info/top_level.txt
jack_social_checker-0.1.0.dist-info/RECORD
