Metadata-Version: 2.4
Name: jack_social_checker
Version: 0.1.0
Summary: A Python tool for checking if an email is linked to Snapchat, Twitter, or Instagram accounts.
Author: JACK
Author-email: gsksvsksksj@gmail.com
Classifier: Programming Language :: Python :: 3
Classifier: License :: OSI Approved :: MIT License
Classifier: Operating System :: OS Independent
Requires-Python: >=3.6
Requires-Dist: requests
Dynamic: author
Dynamic: author-email
Dynamic: classifier
Dynamic: description
Dynamic: description-content-type
Dynamic: requires-dist
Dynamic: requires-python
Dynamic: summary
